refi_calculator/__init__.py
refi_calculator/cli.py
refi_calculator/core/__init__.py
refi_calculator/core/calculations.py
refi_calculator/core/charts.py
refi_calculator/core/market/__init__.py
refi_calculator/core/market/constants.py
refi_calculator/core/market/fred.py
refi_calculator/core/models.py
refi_calculator/environment.py
refi_calculator/gui/__init__.py
refi_calculator/gui/app.py
refi_calculator/gui/builders/__init__.py
refi_calculator/gui/builders/analysis_tab.py
refi_calculator/gui/builders/helpers.py
refi_calculator/gui/builders/info_tab.py
refi_calculator/gui/builders/main_tab.py
refi_calculator/gui/builders/market_tab.py
refi_calculator/gui/builders/options_tab.py
refi_calculator/gui/builders/visuals_tab.py
refi_calculator/gui/chart.py
refi_calculator/gui/market_chart.py
refi_calculator/web/__init__.py
refi_calculator/web/app.py
refi_calculator/web/calculator.py
refi_calculator/web/formatting.py
refi_calculator/web/info.py
refi_calculator/web/market.py
refi_calculator/web/results.py
refi_calculator/web/runner.py
refi_calculator-0.9.3.dist-info/METADATA
refi_calculator-0.9.3.dist-info/WHEEL
refi_calculator-0.9.3.dist-info/entry_points.txt
refi_calculator-0.9.3.dist-info/licenses/LICENSE.txt
refi_calculator-0.9.3.dist-info/RECORD
