Metadata-Version: 2.4
Name: refi-calculator
Version: 0.9.3
Summary: Refi Calculator Package.
License-Expression: Apache-2.0
License-File: LICENSE.txt
Keywords: Refi Calculator
Author: Jordan Pflum
Author-email: jordandpflum@gmail.com
Maintainer: Jordan Pflum
Maintainer-email: jordandpflum@gmail.com
Requires-Python: >=3.13, <3.14
Classifier: Programming Language :: Python :: 3.13
Classifier: License :: OSI Approved :: Apache Software License
Provides-Extra: gui
Provides-Extra: web
Requires-Dist: plotly (>=5.18.0,<6.0.0) ; extra == "web"
Requires-Dist: streamlit (>=1.28.0,<2.0.0) ; extra == "web"
Project-URL: Homepage, https://github.com/jordandpflum/refi-calculator
Project-URL: Repository, https://github.com/jordandpflum/refi-calculator
